{
  "e2e/changeLanguage.cy.ts": { "time": 3445, "weight": 1 },
  "e2e/createLine.cy.ts": { "time": 7499, "weight": 3 },
  "e2e/createRoute.cy.ts": { "time": 63347, "weight": 26 },
  "e2e/createStop.cy.ts": { "time": 42289, "weight": 17 },
  "e2e/editLineInfo.cy.ts": { "time": 7034, "weight": 2 },
  "e2e/editRoute.cy.ts": { "time": 29939, "weight": 12 },
  "e2e/editRouteShape.cy.ts": { "time": 21871, "weight": 9 },
  "e2e/editStop.cy.ts": { "time": 63985, "weight": 26 },
  "e2e/hastusExport.cy.ts": { "time": 37341, "weight": 15 },
  "e2e/login.cy.ts": { "time": 2330, "weight": 0 },
  "e2e/routeStops.cy.ts": { "time": 34294, "weight": 14 },
  "e2e/searchRoutesAndLines.cy.ts": { "time": 3627, "weight": 1 },
  "e2e/timetableImport.cy.ts": { "time": 10197, "weight": 4 },
  "e2e/timetablePassingTimes.cy.ts": { "time": 9131, "weight": 3 }
}
